ggml/__init__.py
ggml/classification/__init__.py
ggml/clustering/__init__.py
ggml/common/__init__.py
ggml/core/__init__.py
ggml/inference/__init__.py
ggml/metrics/__init__.py
ggml/model_selection/__init__.py
ggml/preprocessing/__init__.py
ggml/regression/__init__.py
ggml/storage/__init__.py
ggml-0.0.3.dist-info/DESCRIPTION.rst
ggml-0.0.3.dist-info/METADATA
ggml-0.0.3.dist-info/RECORD
ggml-0.0.3.dist-info/WHEEL
ggml-0.0.3.dist-info/metadata.json
ggml-0.0.3.dist-info/top_level.txt
