Metadata-Version: 2.0
Name: ggml
Version: 0.0.3
Summary: GridGain ML Python API
Home-page: https://github.com/gridgain/ml-python-api/tree/master/python
Author: Anton Dmitriev
Author-email: dmitrievanthony@gmail.com
License: UNKNOWN
Platform: UNKNOWN
Classifier: Programming Language :: Python
Classifier: Programming Language :: Python :: 3
Classifier: Programming Language :: Python :: 3.4
Classifier: Programming Language :: Python :: 3.5
Classifier: Programming Language :: Python :: 3.6
Classifier: Programming Language :: Python :: 3 :: Only
Classifier: Intended Audience :: Developers
Classifier: Topic :: Database :: Front-Ends
Classifier: Topic :: Software Development :: Libraries :: Python Modules
Classifier: License :: OSI Approved :: Apache Software License
Classifier: Operating System :: OS Independent
Requires-Python: >=3.4
Requires-Dist: pandas (==0.24.2)
Requires-Dist: py4j (==0.10.8.1)
Provides-Extra: docs
Requires-Dist: Sphinx (==1.7.5); extra == 'docs'
Requires-Dist: sphinxcontrib-fulltoc (==1.2.0); extra == 'docs'
